{
  "subjects": {
    "0": "Физическая культура",
    "1": "Английский",
    "2": "Программирование",
    "3": "Мат. логика",
    "4": "Архитектура ЭВМ",
    "5": "Немецкий"
  },
  "subgroups": {
    "1": "Первая подгруппа",
    "2": "Вторая подгруппа"
  },
  "timers": {
    "1": {
      "duration": 90,
      "1": [8,30],
      "2": [10,10],
      "3": [12,0],
      "4": [14,0],
      "5": [15,20],
      "6": [8,30]
    }

  },
  "schedule": {
    "monday": {
      "timer": "1",
      "1": {
        "class": "5",
        "type": "2",
        "room": "200",
        "parity": ["1","2"],
        "subgroups": ["1","2"]
      },
      "2": {
        "class": "3",
        "type": "2",
        "room": "400",
        "parity": ["1","2"],
        "subgroups": ["1","2"]
      }
    },
    "tuesday": {
      "timer": "1"
    },
    "wednesday": {
      "timer": "1"
    },
    "tuesday": {
      "timer": "1"
    },
    "friday": {
      "timer": "1"
    },
    "saturday": {
      "timer": "1"
    },
    "sunday": {
      "timer": "1"
    }
  }
}
